etl_gen/__init__.py
etl_gen/commands/__init__.py
etl_gen/commands/address.py
etl_gen/commands/dateformat.py
etl_gen/commands/float.py
etl_gen/commands/ip.py
etl_gen/commands/mixedhtml.py
etl_gen/commands/mixedJson.py
etl_gen/commands/mixedxml.py
etl_gen/commands/ssn.py
etl_gen/commands/tools.py
etl_gen/main.py
etl_gen/resources/address_data
etl_gen/resources/address_data_xml/0.xml
etl_gen/resources/address_data_xml/1.xml
etl_gen/resources/address_data_xml/10.xml
etl_gen/resources/address_data_xml/11.xml
etl_gen/resources/address_data_xml/12.xml
etl_gen/resources/address_data_xml/13.xml
etl_gen/resources/address_data_xml/14.xml
etl_gen/resources/address_data_xml/2.xml
etl_gen/resources/address_data_xml/3.xml
etl_gen/resources/address_data_xml/4.xml
etl_gen/resources/address_data_xml/5.xml
etl_gen/resources/address_data_xml/6.xml
etl_gen/resources/address_data_xml/7.xml
etl_gen/resources/address_data_xml/8.xml
etl_gen/resources/address_data_xml/9.xml
etl_gen/resources/html_list/1.html
etl_gen/resources/html_list/10.html
etl_gen/resources/html_list/100.html
etl_gen/resources/html_list/101.html
etl_gen/resources/html_list/102.html
etl_gen/resources/html_list/103.html
etl_gen/resources/html_list/104.html
etl_gen/resources/html_list/105.html
etl_gen/resources/html_list/106.html
etl_gen/resources/html_list/107.html
etl_gen/resources/html_list/108.html
etl_gen/resources/html_list/109.html
etl_gen/resources/html_list/11.html
etl_gen/resources/html_list/110.html
etl_gen/resources/html_list/111.html
etl_gen/resources/html_list/112.html
etl_gen/resources/html_list/113.html
etl_gen/resources/html_list/114.html
etl_gen/resources/html_list/115.html
etl_gen/resources/html_list/116.html
etl_gen/resources/html_list/117.html
etl_gen/resources/html_list/118.html
etl_gen/resources/html_list/119.html
etl_gen/resources/html_list/12.html
etl_gen/resources/html_list/120.html
etl_gen/resources/html_list/121.html
etl_gen/resources/html_list/122.html
etl_gen/resources/html_list/123.html
etl_gen-0.1.12.dist-info/entry_points.txt
etl_gen-0.1.12.dist-info/WHEEL
etl_gen-0.1.12.dist-info/METADATA
etl_gen-0.1.12.dist-info/RECORD
